tmxpy/__init__.py
tmxpy/tmxpy.py
tmxpy-0.2.6.dist-info/LICENSE
tmxpy-0.2.6.dist-info/METADATA
tmxpy-0.2.6.dist-info/WHEEL
tmxpy-0.2.6.dist-info/top_level.txt
tmxpy-0.2.6.dist-info/RECORD
