Metadata-Version: 2.1
Name: tmxpy
Version: 0.2.6
Summary: A Python library for reading and writing TMX files.
Author-email: AnotherPillow <redacted@email.xyz>
Project-URL: Homepage, https://github.com/AnotherPillow/tmxpy
Project-URL: Bug Tracker, https://github.com/AnotherPillow/tmxpy/issues
Classifier: Programming Language :: Python :: 3
Classifier: License :: OSI Approved :: GNU General Public License v3 (GPLv3)
Classifier: Operating System :: OS Independent
Requires-Python: >=3.8
License-File: LICENSE
Requires-Dist: BeautifulSoup4
Requires-Dist: lxml
Requires-Dist: Pillow
